{".class":"MypyFile","_fullname":"django.utils.ipv6","future_import_flags":[],"is_partial_stub_package":false,"is_stub":false,"names":{".class":"SymbolTable","MAX_IPV6_ADDRESS_LENGTH":{".class":"SymbolTableNode","kind":"Gdef","node":{".class":"Var","flags":["is_ready","is_inferred","has_explicit_value"],"fullname":"django.utils.ipv6.MAX_IPV6_ADDRESS_LENGTH","name":"MAX_IPV6_ADDRESS_LENGTH","type":"builtins.int"}},"ValidationError":{".class":"SymbolTableNode","cross_ref":"django.core.exceptions.ValidationError","kind":"Gdef"},"_":{".class":"SymbolTableNode","cross_ref":"django.utils.translation.gettext_lazy","kind":"Gdef"},"__annotations__":{".class":"SymbolTableNode","kind":"Gdef","node":{".class":"Var","flags":["is_ready"],"fullname":"django.utils.ipv6.__annotations__","name":"__annotations__","type":{".class":"Instance","args":["builtins.str",{".class":"AnyType","missing_import_name":null,"source_any":null,"type_of_any":6}],"extra_attrs":null,"type_ref":"builtins.dict"}}},"__doc__":{".class":"SymbolTableNode","kind":"Gdef","node":{".class":"Var","flags":["is_ready"],"fullname":"django.utils.ipv6.__doc__","name":"__doc__","type":"builtins.str"}},"__file__":{".class":"SymbolTableNode","kind":"Gdef","node":{".class":"Var","flags":["is_ready"],"fullname":"django.utils.ipv6.__file__","name":"__file__","type":"builtins.str"}},"__name__":{".class":"SymbolTableNode","kind":"Gdef","node":{".class":"Var","flags":["is_ready"],"fullname":"django.utils.ipv6.__name__","name":"__name__","type":"builtins.str"}},"__package__":{".class":"SymbolTableNode","kind":"Gdef","node":{".class":"Var","flags":["is_ready"],"fullname":"django.utils.ipv6.__package__","name":"__package__","type":"builtins.str"}},"__spec__":{".class":"SymbolTableNode","kind":"Gdef","node":{".class":"Var","flags":["is_ready"],"fullname":"django.utils.ipv6.__spec__","name":"__spec__","type":"importlib.machinery.ModuleSpec"}},"_ipv6_address_from_str":{".class":"SymbolTableNode","kind":"Gdef","node":{".class":"FuncDef","abstract_status":0,"arg_kinds":[0,1],"arg_names":["ip_str","max_length"],"dataclass_transform_spec":null,"flags":[],"fullname":"django.utils.ipv6._ipv6_address_from_str","name":"_ipv6_address_from_str","type":null}},"clean_ipv6_address":{".class":"SymbolTableNode","kind":"Gdef","node":{".class":"FuncDef","abstract_status":0,"arg_kinds":[0,1,1,1],"arg_names":["ip_str","unpack_ipv4","error_message","max_length"],"dataclass_transform_spec":null,"flags":[],"fullname":"django.utils.ipv6.clean_ipv6_address","name":"clean_ipv6_address","type":null}},"ipaddress":{".class":"SymbolTableNode","cross_ref":"ipaddress","kind":"Gdef"},"is_valid_ipv6_address":{".class":"SymbolTableNode","kind":"Gdef","node":{".class":"FuncDef","abstract_status":0,"arg_kinds":[0],"arg_names":["ip_addr"],"dataclass_transform_spec":null,"flags":[],"fullname":"django.utils.ipv6.is_valid_ipv6_address","name":"is_valid_ipv6_address","type":null}}},"path":"/home/zbyszek/Development/django-pgallery/.venv/lib/python3.13/site-packages/django/utils/ipv6.py"}