[
    {
        "accuracy": 0.2957,
        "batch": 512,
        "dropout": 0.01104070755969766,
        "duration": 59183223572,
        "lr": 0.061501818525041614,
        "momentum": 0.33808574224783183,
        "transform": "norm_256_flip",
        "uid": "8be7f1b51d3842fe737d7b20efdfd4b8"
    },
    {
        "accuracy": 0.2691,
        "batch": 512,
        "dropout": 0.06048890534336371,
        "duration": 58876360457,
        "lr": 0.014682910596673232,
        "momentum": 0.8983637617206579,
        "transform": "norm_256_flip",
        "uid": "794d5eb7de9fef5c71641ad897596dd0"
    },
    {
        "accuracy": 0.1461,
        "batch": 512,
        "dropout": 0.03910969074200349,
        "duration": 58916207332,
        "lr": 0.011749518368741151,
        "momentum": 0.17438189534392634,
        "transform": "norm_256_flip",
        "uid": "d830a530f8f3333273495762faa5c4bd"
    },
    {
        "accuracy": 0.1315,
        "batch": 512,
        "dropout": 0.18650334904016241,
        "duration": 58671656928,
        "lr": 0.36384122864805174,
        "momentum": 0.5251577848516716,
        "transform": "norm_256_flip",
        "uid": "58201cdc026d8e038c10baf303c88f43"
    },
    {
        "accuracy": 0.1271,
        "batch": 512,
        "dropout": 0.31201546621129117,
        "duration": 58840347048,
        "lr": 0.0027442941445299826,
        "momentum": 0.6772435150122009,
        "transform": "norm_256_flip",
        "uid": "5b3afb56a2c8dee48eb9edb75e3b45f7"
    },
    {
        "accuracy": 0.1255,
        "batch": 512,
        "dropout": 0.3603820465876928,
        "duration": 58937885295,
        "lr": 0.0025337193084483205,
        "momentum": 0.4282642371875852,
        "transform": "norm_256_flip",
        "uid": "13e6d13298769e49e5c37810bbeb4690"
    }
]