[
    {
        "accuracy": 0.3161783439490446,
        "batch": 1,
        "dropout": 0.04244817711648996,
        "duration": 169491807443,
        "lr": 0.000355448840084766,
        "momentum": 0.9402059353894461,
        "transform": "norm_32_flip",
        "uid": "3aaca3a2e80f07b4c718adde71929cea"
    },
    {
        "accuracy": 0.31261146496815284,
        "batch": 32,
        "dropout": 0.349855104412459,
        "duration": 86152468385,
        "lr": 0.02561041153464553,
        "momentum": 0.07118616415620949,
        "transform": "norm_64_flip",
        "uid": "8ca19b38b7c770ce3fad7263663d09e2"
    }
]